aliceplex/serialize/__init__.py
aliceplex/serialize/base.py
aliceplex/serialize/util.py
aliceplex/serialize/xml.py
aliceplex/serialize/yml.py
aliceplex_serialize-2.2.0.dist-info/LICENSE
aliceplex_serialize-2.2.0.dist-info/METADATA
aliceplex_serialize-2.2.0.dist-info/WHEEL
aliceplex_serialize-2.2.0.dist-info/top_level.txt
aliceplex_serialize-2.2.0.dist-info/RECORD
